fspy/__init__.py
fspy/response_models.py
fspy/solver.py
fspy/solver_exceptions.py
fspy-0.4.0.dist-info/LICENSE
fspy-0.4.0.dist-info/METADATA
fspy-0.4.0.dist-info/WHEEL
fspy-0.4.0.dist-info/top_level.txt
fspy-0.4.0.dist-info/RECORD
