Metadata-Version: 2.1
Name: fspy
Version: 0.4.0
Summary: A FlareSolverr wrapper for Python.
Author: NandeMD
License: GNU GENERAL PUBLIC LICENSE
Project-URL: Homepage, https://github.com/NandeMD/FSPy
Project-URL: Repository, https://github.com/NandeMD/FSPy
Keywords: wrapper,flaresolverr
Classifier: Development Status :: 4 - Beta
Classifier: Intended Audience :: Developers
Classifier: License :: OSI Approved :: GNU General Public License v3 (GPLv3)
Classifier: Operating System :: OS Independent
Classifier: Programming Language :: Python :: 3.8
Classifier: Programming Language :: Python :: 3.9
Classifier: Programming Language :: Python :: 3.10
Classifier: Programming Language :: Python :: 3.11
Classifier: Topic :: Utilities
Classifier: Typing :: Typed
Requires-Python: >=3.8
License-File: LICENSE
Requires-Dist: certifi >=2017.4.17
Requires-Dist: charset-normalizer <4,>=2
Requires-Dist: idna <4,>=2.5
Requires-Dist: urllib3 <3,>=1.21.1
Requires-Dist: requests >=2.9.2
Requires-Dist: orjson >=3.8.0
